pocean/__init__.py
pocean/_version.py
pocean/cf.py
pocean/dataset.py
pocean/meta.py
pocean/utils.py
pocean/dsg/__init__.py
pocean/dsg/utils.py
pocean/dsg/profile/__init__.py
pocean/dsg/profile/im.py
pocean/dsg/profile/om.py
pocean/dsg/timeseries/__init__.py
pocean/dsg/timeseries/cr.py
pocean/dsg/timeseries/im.py
pocean/dsg/timeseries/ir.py
pocean/dsg/timeseries/om.py
pocean/dsg/timeseriesProfile/__init__.py
pocean/dsg/timeseriesProfile/im.py
pocean/dsg/timeseriesProfile/om.py
pocean/dsg/timeseriesProfile/r.py
pocean/dsg/trajectory/__init__.py
pocean/dsg/trajectory/cr.py
pocean/dsg/trajectory/im.py
pocean/dsg/trajectory/ir.py
pocean/dsg/trajectoryProfile/__init__.py
pocean/dsg/trajectoryProfile/cr.py
pocean/grid/__init__.py
pocean_core-2025.1.dist-info/LICENSE.txt
pocean_core-2025.1.dist-info/METADATA
pocean_core-2025.1.dist-info/WHEEL
pocean_core-2025.1.dist-info/top_level.txt
pocean_core-2025.1.dist-info/RECORD
