Metadata-Version: 2.2
Name: pocean-core
Version: 2025.1
Summary: A python framework for working with met-ocean data
Author-email: Kyle Wilcox <kyle@axds.co>
License: The MIT License (MIT)
Project-URL: documentation, https://pyoceans.github.io/pocean-core
Project-URL: homepage, https://pypi.org/project/pocean-core/
Project-URL: repository, https://github.com/pyoceans/pocean-core
Classifier: Programming Language :: Python :: 3 :: Only
Classifier: Programming Language :: Python :: 3.9
Classifier: Programming Language :: Python :: 3.10
Classifier: Programming Language :: Python :: 3.11
Classifier: Programming Language :: Python :: 3.12
Classifier: Programming Language :: Python :: 3.13
Requires-Python: >=3.9
License-File: LICENSE.txt
Requires-Dist: cftime>=1.2.1
Requires-Dist: netcdf4
Requires-Dist: numpy>=1.20
Requires-Dist: pandas>=1.0.5
Requires-Dist: python-dateutil
Requires-Dist: pytz
Requires-Dist: shapely>=1.8
Requires-Dist: simplejson
